src/__init__.py
src/factory/__init__.py
src/factory/config_loader.py
src/factory/database_factory.py
src/factory/datasource_manager.py
src/model/__init__.py
src/model/database_config.py
src/strategy/__init__.py
src/strategy/database_strategy.py
src/strategy/mysql_strategy.py
src/tools/mysql_tools.py
database_mcp_server-1.0.2.dist-info/METADATA
database_mcp_server-1.0.2.dist-info/WHEEL
database_mcp_server-1.0.2.dist-info/entry_points.txt
database_mcp_server-1.0.2.dist-info/licenses/LICENSE
database_mcp_server-1.0.2.dist-info/RECORD
