Metadata-Version: 2.4
Name: database-mcp-server
Version: 1.0.2
Summary: Database MCP Server for SQL operations
License-File: LICENSE
Requires-Python: >=3.13
Requires-Dist: dbutils>=3.1.1
Requires-Dist: fastmcp>=2.11.0
Requires-Dist: mcp[cli]>=1.12.2
Requires-Dist: pymysql>=1.1.1
Requires-Dist: python-dotenv>=1.1.1
Requires-Dist: pyyaml>=6.0.1
